aige/__init__.py
aige/core.py
aige/literature.py
aige/summarize.py
aige/enrichment_tools/__init__.py
aige/enrichment_tools/enrichr.py
aige/enrichment_tools/gprofiler.py
aige/enrichment_tools/toppfun.py
ai_gene_enrichment-0.1.0.dist-info/METADATA
ai_gene_enrichment-0.1.0.dist-info/WHEEL
ai_gene_enrichment-0.1.0.dist-info/top_level.txt
ai_gene_enrichment-0.1.0.dist-info/RECORD
