Metadata-Version: 2.1
Name: ai-gene-enrichment
Version: 0.1.0
Summary: A comprehensive tool for running gene enrichment analysis workflows using multiple enrichment tools and AI-powered summarization
Home-page: https://github.com/calvinboyce/ai-gene-enrichment
Author: Calvin Boyce
Author-email: Calvin Boyce <cboyce3@mgh.harvard.edu>
Maintainer-email: Calvin Boyce <cboyce3@mgh.harvard.edu>
License: CC-BY-NC-4.0
Project-URL: Homepage, https://github.com/calvinboyce/ai-gene-enrichment
Project-URL: Repository, https://github.com/calvinboyce/ai-gene-enrichment
Project-URL: Documentation, https://github.com/calvinboyce/ai-gene-enrichment#readme
Project-URL: Issues, https://github.com/calvinboyce/ai-gene-enrichment/issues
Keywords: bioinformatics,gene-enrichment,ai,genomics,enrichment-analysis
Platform: any
Classifier: Development Status :: 3 - Alpha
Classifier: Intended Audience :: Science/Research
Classifier: Topic :: Scientific/Engineering :: Bio-Informatics
Classifier: Programming Language :: Python :: 3
Classifier: Programming Language :: Python :: 3.8
Classifier: Programming Language :: Python :: 3.9
Classifier: Programming Language :: Python :: 3.10
Classifier: Programming Language :: Python :: 3.11
Classifier: Programming Language :: Python :: 3.12
Classifier: Operating System :: OS Independent
Requires-Python: >=3.8
Requires-Dist: openai>=1.0.0
Requires-Dist: requests>=2.31.0
Requires-Dist: python-dotenv>=1.0.0
Requires-Dist: biopython>=1.82
Requires-Dist: gprofiler-official>=1.0.0
Requires-Dist: openpyxl>=3.1.5
Provides-Extra: dev
Requires-Dist: pytest>=7.0.0; extra == "dev"
Requires-Dist: pytest-cov>=4.0.0; extra == "dev"
Requires-Dist: black>=23.0.0; extra == "dev"
Requires-Dist: flake8>=6.0.0; extra == "dev"
Requires-Dist: mypy>=1.0.0; extra == "dev"
